jsonstore_socket/__init__.py
jsonstore_socket/core.py
jsonstore_socket-0.0.2.dist-info/DESCRIPTION.rst
jsonstore_socket-0.0.2.dist-info/METADATA
jsonstore_socket-0.0.2.dist-info/RECORD
jsonstore_socket-0.0.2.dist-info/WHEEL
jsonstore_socket-0.0.2.dist-info/metadata.json
jsonstore_socket-0.0.2.dist-info/top_level.txt
